aiogram_dialog/__init__.py
aiogram_dialog/about.py
aiogram_dialog/dialog.py
aiogram_dialog/py.typed
aiogram_dialog/setup.py
aiogram_dialog/utils.py
aiogram_dialog/window.py
aiogram_dialog/api/__init__.py
aiogram_dialog/api/exceptions.py
aiogram_dialog/api/entities/__init__.py
aiogram_dialog/api/entities/access.py
aiogram_dialog/api/entities/context.py
aiogram_dialog/api/entities/events.py
aiogram_dialog/api/entities/launch_mode.py
aiogram_dialog/api/entities/media.py
aiogram_dialog/api/entities/modes.py
aiogram_dialog/api/entities/new_message.py
aiogram_dialog/api/entities/stack.py
aiogram_dialog/api/entities/update_event.py
aiogram_dialog/api/internal/__init__.py
aiogram_dialog/api/internal/fake_data.py
aiogram_dialog/api/internal/manager.py
aiogram_dialog/api/internal/middleware.py
aiogram_dialog/api/internal/widgets.py
aiogram_dialog/api/internal/window.py
aiogram_dialog/api/protocols/__init__.py
aiogram_dialog/api/protocols/dialog.py
aiogram_dialog/api/protocols/manager.py
aiogram_dialog/api/protocols/media.py
aiogram_dialog/api/protocols/message_manager.py
aiogram_dialog/api/protocols/registry.py
aiogram_dialog/api/protocols/stack_access.py
aiogram_dialog/context/__init__.py
aiogram_dialog/context/access_validator.py
aiogram_dialog/context/intent_filter.py
aiogram_dialog/context/intent_middleware.py
aiogram_dialog/context/media_storage.py
aiogram_dialog/context/storage.py
aiogram_dialog/manager/__init__.py
aiogram_dialog/manager/bg_manager.py
aiogram_dialog/manager/manager.py
aiogram_dialog/manager/manager_factory.py
aiogram_dialog/manager/manager_middleware.py
aiogram_dialog/manager/message_manager.py
aiogram_dialog/manager/sub_manager.py
aiogram_dialog/manager/update_handler.py
aiogram_dialog/manager/updater.py
aiogram_dialog/test_tools/__init__.py
aiogram_dialog/test_tools/bot_client.py
aiogram_dialog/test_tools/keyboard.py
aiogram_dialog/test_tools/memory_storage.py
aiogram_dialog/test_tools/mock_message_manager.py
aiogram_dialog/tools/__init__.py
aiogram_dialog-2.4.0.dist-info/LICENSE
aiogram_dialog-2.4.0.dist-info/METADATA
aiogram_dialog-2.4.0.dist-info/WHEEL
aiogram_dialog-2.4.0.dist-info/entry_points.txt
aiogram_dialog-2.4.0.dist-info/top_level.txt
aiogram_dialog-2.4.0.dist-info/RECORD
