Metadata-Version: 2.1
Name: aiogram_dialog
Version: 2.4.0
Summary: Telegram bot UI framework on top of aiogram
Author-email: Andrey Tikhonov <17@itishka.org>
License: Apache-2.0
Project-URL: Homepage, https://github.com/tishka17/aiogram_dialog
Project-URL: Documentation, https://aiogram-dialog.readthedocs.org
Project-URL: Bug Tracker, https://github.com/tishka17/aiogram_dialog/issues
Classifier: Programming Language :: Python :: 3
Classifier: Programming Language :: Python :: 3.9
Classifier: Programming Language :: Python :: 3.10
Classifier: Programming Language :: Python :: 3.11
Classifier: Programming Language :: Python :: 3.12
Classifier: Programming Language :: Python :: 3.13
Classifier: Intended Audience :: Developers
Classifier: License :: OSI Approved :: Apache Software License
Classifier: Operating System :: OS Independent
Requires-Python: >=3.9
License-File: LICENSE
Requires-Dist: aiogram>=3.14.0
Requires-Dist: jinja2
Requires-Dist: cachetools<6.0.0,>=4.0.0
Provides-Extra: tools
Requires-Dist: diagrams; extra == "tools"
Requires-Dist: aiohttp; extra == "tools"
